EncroX/__init__.py
EncroX/aes.py
EncroX/aes.pyi
EncroX/ecc.py
EncroX/ecc.pyi
EncroX/rsa.py
EncroX/rsa.pyi
EncroX-1.1.0.dist-info/LICENSE
EncroX-1.1.0.dist-info/METADATA
EncroX-1.1.0.dist-info/WHEEL
EncroX-1.1.0.dist-info/top_level.txt
EncroX-1.1.0.dist-info/RECORD
