Metadata-Version: 2.1
Name: EncroX
Version: 1.1.0
Summary: EncroX是一个强大的加密拓展工具，旨在为您的应用程序和系统提供可靠的加密和解密功能。通过集成各种密码学算法和密钥管理方法，EncroX使您能够轻松地进行数据加密、解密和安全通信。
Home-page: https://github.com/KindLittleTurtle/EncroX
Author: 核善的小兲
Author-email: hsdxt@mwtour.cn
License: AGPL3.0
License-File: LICENSE
Requires-Dist: cryptography
